{
  "event_id": "019e16a9-aa20-7041-9eed-edeb258ad24a",
  "occurred_at": "2026-05-11T10:51:18.432162364Z",
  "type": "idx.knot_head",
  "data": {
    "blocked_from_state": null,
    "deferred_from_state": null,
    "gate": {
      "owner_kind": "agent"
    },
    "invariants": [],
    "knot_id": "knots-ac54",
    "profile_id": "lease",
    "state": "lease_terminated",
    "terminal": true,
    "title": "Lease: foolery:terminal_manager_take:term-1778494883965-23tdza",
    "type": "lease",
    "updated_at": "2026-05-11T10:51:18.432162364Z",
    "workflow_id": "lease_sdlc"
  }
}
