{
  "event_id": "019e7ee3-b0ce-7790-b0dd-c76efb3c9954",
  "occurred_at": "2026-05-31T16:35:11.69418435Z",
  "type": "idx.knot_head",
  "data": {
    "blocked_from_state": null,
    "deferred_from_state": null,
    "gate": {
      "owner_kind": "agent"
    },
    "invariants": [],
    "knot_id": "knots-c3f6",
    "profile_id": "lease",
    "state": "lease_terminated",
    "terminal": true,
    "title": "Lease: foolery:terminal_manager_take:term-1780242439836-pioov4",
    "type": "lease",
    "updated_at": "2026-05-31T16:35:11.69418435Z",
    "workflow_id": "lease_sdlc"
  }
}
