{
  "event_id": "019eac11-c4f4-7e63-b899-6ebcdea337f1",
  "occurred_at": "2026-06-09T11:08:26.228833357Z",
  "type": "idx.knot_head",
  "data": {
    "blocked_from_state": null,
    "deferred_from_state": null,
    "gate": {
      "owner_kind": "agent"
    },
    "invariants": [],
    "knot_id": "knots-7048",
    "next_step_metadata": {
      "action_kind": "produce",
      "action_state": "shipment",
      "output": {
        "artifact_type": "remote_main"
      },
      "owner": {
        "agent_model": null,
        "agent_name": null,
        "agent_version": null,
        "kind": "agent"
      }
    },
    "profile_id": "autopilot",
    "state": "implementation_review",
    "step_metadata": {
      "action_kind": "gate",
      "action_state": "implementation_review",
      "output": {
        "artifact_type": "remote_main"
      },
      "owner": {
        "agent_model": null,
        "agent_name": null,
        "agent_version": null,
        "kind": "agent"
      }
    },
    "terminal": false,
    "title": "Document leases and handoff capsules in the knots agent skills",
    "type": "work",
    "updated_at": "2026-06-09T11:08:26.228833357Z",
    "workflow_id": "work_sdlc"
  },
  "precondition": {
    "profile_etag": "019eac11-5bbb-7720-9512-16da69304d49"
  }
}
