{
  "event_id": "019d9b03-08ef-7b52-b60a-5ef854747a47",
  "occurred_at": "2026-04-17T10:36:00.623643Z",
  "type": "idx.knot_head",
  "data": {
    "blocked_from_state": null,
    "deferred_from_state": null,
    "gate": {
      "owner_kind": "agent"
    },
    "invariants": [],
    "knot_id": "knots-2a30",
    "next_step_metadata": {
      "action_kind": "produce",
      "action_state": "shipment",
      "output": {
        "artifact_type": "remote_main"
      },
      "owner": {
        "agent_model": null,
        "agent_name": null,
        "agent_version": null,
        "kind": "agent"
      }
    },
    "profile_id": "autopilot",
    "state": "ready_for_shipment",
    "step_metadata": {
      "action_kind": "produce",
      "action_state": "shipment",
      "output": {
        "artifact_type": "remote_main"
      },
      "owner": {
        "agent_model": null,
        "agent_name": null,
        "agent_version": null,
        "kind": "agent"
      }
    },
    "terminal": false,
    "title": "kno doctor --fix not handling cold_tier_imbalance edge case",
    "type": "work",
    "updated_at": "2026-04-17T10:36:00.623643Z",
    "workflow_id": "work_sdlc"
  }
}
