{
  "event_id": "019d9a58-66b7-7c10-88af-2d066698f223",
  "occurred_at": "2026-04-17T07:29:37.96921Z",
  "type": "idx.knot_head",
  "data": {
    "blocked_from_state": null,
    "deferred_from_state": null,
    "gate": {
      "owner_kind": "agent"
    },
    "invariants": [],
    "knot_id": "knots-9f61",
    "next_step_metadata": {
      "action_kind": "gate",
      "action_state": "implementation_review",
      "output": {
        "artifact_type": "remote_main"
      },
      "owner": {
        "agent_model": null,
        "agent_name": null,
        "agent_version": null,
        "kind": "agent"
      }
    },
    "profile_id": "autopilot",
    "state": "implementation",
    "step_metadata": {
      "action_kind": "produce",
      "action_state": "implementation",
      "output": {
        "artifact_type": "remote_main"
      },
      "owner": {
        "agent_model": null,
        "agent_name": null,
        "agent_version": null,
        "kind": "agent"
      }
    },
    "terminal": false,
    "title": "Add ready_for_orchestration and orchestration states to execution_plan_sdlc workflow",
    "type": "work",
    "updated_at": "2026-04-17T07:29:37.96921Z",
    "workflow_id": "work_sdlc"
  }
}
