{
  "event_id": "019f2297-a044-7e62-8b15-aebcd09a5d09",
  "occurred_at": "2026-07-02T11:29:50.148145Z",
  "type": "idx.knot_head",
  "data": {
    "blocked_from_state": null,
    "deferred_from_state": null,
    "gate": {
      "owner_kind": "agent"
    },
    "invariants": [],
    "knot_id": "knots-fb31",
    "next_step_metadata": {
      "action_kind": "produce",
      "action_state": "lease_active",
      "output": {
        "artifact_type": ""
      },
      "owner": {
        "agent_model": null,
        "agent_name": null,
        "agent_version": null,
        "kind": "agent"
      }
    },
    "profile_id": "lease",
    "state": "lease_ready",
    "step_metadata": {
      "action_kind": "produce",
      "action_state": "lease_active",
      "output": {
        "artifact_type": ""
      },
      "owner": {
        "agent_model": null,
        "agent_name": null,
        "agent_version": null,
        "kind": "agent"
      }
    },
    "terminal": false,
    "title": "Lease: codex-correct-4d3d",
    "type": "lease",
    "updated_at": "2026-07-02T11:29:50.148145Z",
    "workflow_id": "lease_sdlc"
  }
}
