{
  "event_id": "019e0620-50ea-7312-b0d5-82da060200a4",
  "occurred_at": "2026-05-08T05:47:21.700752Z",
  "type": "idx.knot_head",
  "data": {
    "blocked_from_state": null,
    "deferred_from_state": null,
    "gate": {
      "owner_kind": "agent"
    },
    "invariants": [],
    "knot_id": "knots-e935",
    "next_step_metadata": {
      "action_kind": "gate",
      "action_state": "shipment_review",
      "output": {
        "artifact_type": "remote_main"
      },
      "owner": {
        "agent_model": null,
        "agent_name": null,
        "agent_version": null,
        "kind": "agent"
      }
    },
    "profile_id": "autopilot",
    "state": "shipment",
    "step_metadata": {
      "action_kind": "produce",
      "action_state": "shipment",
      "output": {
        "artifact_type": "remote_main"
      },
      "owner": {
        "agent_model": null,
        "agent_name": null,
        "agent_version": null,
        "kind": "agent"
      }
    },
    "terminal": false,
    "title": "Fix active lease metadata JSON",
    "type": "work",
    "updated_at": "2026-05-08T05:47:21.700752Z",
    "workflow_id": "work_sdlc"
  }
}
